{
    "Centro": [-3.7275, -38.5275],
    "Barra do Ceará": [-3.7022, -38.5833],
    "Moura Brasil": [-3.7170, -38.5300],
    "Pirambu": [-3.7088, -38.5500],
    "Cristo Redentor": [-3.7150, -38.5550],
    "Carlito Pamplona": [-3.7180, -38.5480],
    "Jacarecanga": [-3.7130, -38.5400],
    "Meireles": [-3.7250, -38.4950],
    "Aldeota": [-3.7350, -38.5000],
    "Varjota": [-3.7400, -38.4850],
    "Praia de Iracema": [-3.7200, -38.5100],
    "Mucuripe": [-3.7200, -38.4800],
    "Cais do Porto": [-3.7180, -38.4700],
    "Vicente Pinzon": [-3.7250, -38.4650],
    "Papicu": [-3.7350, -38.4750],
    "De Lourdes": [-3.7400, -38.4700],
    "Dunas": [-3.7420, -38.4600],
    "Cocó": [-3.7500, -38.4750],
    "Cidade 2000": [-3.7550, -38.4650],
    "Manuel Dias Branco": [-3.7500, -38.4600],
    "Praia do Futuro I": [-3.7300, -38.4550],
    "Praia do Futuro II": [-3.7500, -38.4450],
    "Antonio Diogo": [-3.7550, -38.4500],
    "Sabiaguaba": [-3.7700, -38.4350],
    "São João do Tauape": [-3.7600, -38.5000],
    "Dionísio Torres": [-3.7550, -38.5050],
    "Joaquim Távora": [-3.7500, -38.5100],
    "Fátima": [-3.7450, -38.5200],
    "José Bonifácio": [-3.7420, -38.5300],
    "Benfica": [-3.7400, -38.5400],
    "Farias Brito": [-3.7350, -38.5450],
    "Monte Castelo": [-3.7300, -38.5500],
    "São Gerardo": [-3.7320, -38.5550],
    "Ellery": [-3.7280, -38.5600],
    "Álvaro Weyne": [-3.7250, -38.5650],
    "Floresta": [-3.7220, -38.5700],
    "Jardim Guanabara": [-3.7300, -38.5800],
    "Vila Velha": [-3.7350, -38.5900],
    "Quintino Cunha": [-3.7400, -38.5850],
    "Jardim Iracema": [-3.7450, -38.5800],
    "Padre Andrade": [-3.7480, -38.5750],
    "Antônio Bezerra": [-3.7520, -38.5850],
    "Presidente Kennedy": [-3.7500, -38.5700],
    "Parquelândia": [-3.7450, -38.5600],
    "Amadeu Furtado": [-3.7500, -38.5600],
    "Parque Araújo": [-3.7520, -38.5550],
    "Rodolfo Teófilo": [-3.7550, -38.5500],
    "Bela Vista": [-3.7580, -38.5550],
    "Pici": [-3.7600, -38.5650],
    "Dom Lustosa": [-3.7620, -38.5750],
    "Henrique Jorge": [-3.7650, -38.5800],
    "Autran Nunes": [-3.7680, -38.5850],
    "João XXIII": [-3.7700, -38.5900],
    "Jóquei Clube": [-3.7720, -38.5800],
    "Panamericano": [-3.7650, -38.5550],
    "Couto Fernandes": [-3.7620, -38.5500],
    "Damas": [-3.7600, -38.5450],
    "Montese": [-3.7700, -38.5400],
    "Bom Futuro": [-3.7650, -38.5400],
    "Vila União": [-3.7750, -38.5350],
    "Parreão": [-3.7800, -38.5400],
    "Parque Americano": [-3.7550, -38.5200],
    "Itaperi": [-3.7900, -38.5500],
    "Serrinha": [-3.7950, -38.5450],
    "Aeroporto": [-3.7850, -38.5350],
    "Vila Pery": [-3.7780, -38.5500],
    "Parangaba": [-3.7820, -38.5600],
    "Demócrito Rocha": [-3.7750, -38.5700],
    "Lagoa do Opaia": [-3.7900, -38.5400],
    "Maraponga": [-3.8000, -38.5650],
    "Jardim Cearense": [-3.8050, -38.5700],
    "Mondubim": [-3.8100, -38.5750],
    "Vila Manoel Sátiro": [-3.7950, -38.5800],
    "Conjunto Esperança": [-3.8000, -38.5850],
    "Parque São José": [-3.8050, -38.5900],
    "Santa Rosa": [-3.8100, -38.5950],
    "Aracapé": [-3.8150, -38.6000],
    "Presidente Vargas": [-3.8200, -38.5900],
    "Canindezinho": [-3.8250, -38.6050],
    "Parque Santa Maria": [-3.8150, -38.5550],
    "Siqueira": [-3.8300, -38.6100],
    "Granja Lisboa": [-3.8100, -38.6200],
    "Granja Portugal": [-3.7900, -38.6100],
    "Bom Jardim": [-3.8000, -38.6150],
    "Conjunto Ceará I": [-3.7800, -38.6050],
    "Conjunto Ceará II": [-3.7850, -38.6000],
    "Genibaú": [-3.7880, -38.6100],
    "Jardim América": [-3.7550, -38.5300],
    "Benfica": [-3.7400, -38.5400],
    "Prefeito José Walter": [-3.8200, -38.5800],
    "Planalto Ayrton Senna": [-3.8300, -38.5900],
    "Messejana": [-3.8350, -38.5000],
    "Cambeba": [-3.8200, -38.4900],
    "Parque Iracema": [-3.8150, -38.4850],
    "Cidade dos Funcionários": [-3.8050, -38.4950],
    "Cajazeiras": [-3.8100, -38.5100],
    "Alto da Balança": [-3.7800, -38.5150],
    "Aerolândia": [-3.7850, -38.5100],
    "Boa Vista": [-3.8150, -38.5200],
    "Dias Macedo": [-3.8000, -38.5300],
    "Parque Dois Irmãos": [-3.8150, -38.5400],
    "Passaré": [-3.8250, -38.5350],
    "Planalto Horizonte": [-3.8350, -38.5450],
    "Barroso": [-3.8400, -38.5250],
    "Jangurussu": [-3.8450, -38.5350],
    "Conjunto Palmeiras": [-3.8550, -38.5450],
    "Parque Manibura": [-3.8100, -38.4800],
    "José de Alencar": [-3.8200, -38.4750],
    "Lagoa Redonda": [-3.8300, -38.4650],
    "Curió": [-3.8400, -38.4600],
    "Guajeru": [-3.8500, -38.4550],
    "São Bento": [-3.8600, -38.4700],
    "Paupina": [-3.8500, -38.4850],
    "Ancuri": [-3.8650, -38.5100],
    "Pedras": [-3.8750, -38.5050],
    "Santa Maria": [-3.8800, -38.5000],
    "Coaçu": [-3.8450, -38.4500],
    "Edson Queiroz": [-3.7900, -38.4700],
    "Sapiranga": [-3.8100, -38.4500],
    "Alagadiço Novo": [-3.8200, -38.4400],
    "Moura Brasil": [-3.7170, -38.5300]
}
